ks_shop_api/__init__.py
ks_shop_api/base.py
ks_shop_api/request.py
ks_shop_api/schema.py
ks_shop_api/utils.py
ks_shop_api/comment/__init__.py
ks_shop_api/comment/request.py
ks_shop_api/comment/schema.py
ks_shop_api/cs/__init__.py
ks_shop_api/cs/request.py
ks_shop_api/cs/schema.py
ks_shop_api/distribution/__init__.py
ks_shop_api/distribution/request.py
ks_shop_api/distribution/schema.py
ks_shop_api/dropshipping/__init__.py
ks_shop_api/dropshipping/request.py
ks_shop_api/dropshipping/schema.py
ks_shop_api/express/__init__.py
ks_shop_api/express/request.py
ks_shop_api/express/schema.py
ks_shop_api/funds/__init__.py
ks_shop_api/funds/request.py
ks_shop_api/funds/schema.py
ks_shop_api/industry/__init__.py
ks_shop_api/industry/request.py
ks_shop_api/industry/schema.py
ks_shop_api/invoice/__init__.py
ks_shop_api/invoice/request.py
ks_shop_api/invoice/schema.py
ks_shop_api/item/__init__.py
ks_shop_api/item/request.py
ks_shop_api/item/schema.py
ks_shop_api/logistics/__init__.py
ks_shop_api/logistics/request.py
ks_shop_api/logistics/schema.py
ks_shop_api/merchant_sms/__init__.py
ks_shop_api/merchant_sms/request.py
ks_shop_api/merchant_sms/schema.py
ks_shop_api/open_platform_tools/__init__.py
ks_shop_api/open_platform_tools/request.py
ks_shop_api/open_platform_tools/schema.py
ks_shop_api/order/__init__.py
ks_shop_api/order/request.py
ks_shop_api/order/schema.py
ks_shop_api/promotion/__init__.py
ks_shop_api/promotion/request.py
ks_shop_api/promotion/schema.py
ks_shop_api/refund/__init__.py
ks_shop_api/refund/request.py
ks_shop_api/refund/schema.py
ks_shop_api/scm/__init__.py
ks_shop_api/scm/request.py
ks_shop_api/scm/schema.py
ks_shop_api/security/__init__.py
ks_shop_api/security/request.py
ks_shop_api/security/schema.py
ks_shop_api/servicemarket/__init__.py
ks_shop_api/servicemarket/request.py
ks_shop_api/servicemarket/schema.py
ks_shop_api/shop/__init__.py
ks_shop_api/shop/request.py
ks_shop_api/shop/schema.py
ks_shop_api/shoplive/__init__.py
ks_shop_api/shoplive/request.py
ks_shop_python_sdk-0.3.0.dist-info/METADATA
ks_shop_python_sdk-0.3.0.dist-info/WHEEL
ks_shop_python_sdk-0.3.0.dist-info/top_level.txt
ks_shop_python_sdk-0.3.0.dist-info/RECORD
