Metadata-Version: 2.4
Name: ks-shop-python-sdk
Version: 0.3.0
Summary: Kuaishou Shop Python SDK
Requires-Python: >=3.10
Requires-Dist: deprecation>=2.1.0
Requires-Dist: httpx>=0.28.1
Requires-Dist: pydantic>=2.11.7
